tkfeather/__init__.py
tkfeather/icons/activity.png
tkfeather/icons/airplay.png
tkfeather/icons/alert-circle.png
tkfeather/icons/alert-octagon.png
tkfeather/icons/alert-triangle.png
tkfeather/icons/align-center.png
tkfeather/icons/align-justify.png
tkfeather/icons/align-left.png
tkfeather/icons/align-right.png
tkfeather/icons/anchor.png
tkfeather/icons/aperture.png
tkfeather/icons/archive.png
tkfeather/icons/arrow-down-circle.png
tkfeather/icons/arrow-down-left.png
tkfeather/icons/arrow-down-right.png
tkfeather/icons/arrow-down.png
tkfeather/icons/arrow-left-circle.png
tkfeather/icons/arrow-left.png
tkfeather/icons/arrow-right-circle.png
tkfeather/icons/arrow-right.png
tkfeather/icons/arrow-up-circle.png
tkfeather/icons/arrow-up-left.png
tkfeather/icons/arrow-up-right.png
tkfeather/icons/arrow-up.png
tkfeather/icons/at-sign.png
tkfeather/icons/award.png
tkfeather/icons/bar-chart-2.png
tkfeather/icons/bar-chart.png
tkfeather/icons/battery-charging.png
tkfeather/icons/battery.png
tkfeather/icons/bell-off.png
tkfeather/icons/bell.png
tkfeather/icons/bluetooth.png
tkfeather/icons/bold.png
tkfeather/icons/book-open.png
tkfeather/icons/book.png
tkfeather/icons/bookmark.png
tkfeather/icons/box.png
tkfeather/icons/briefcase.png
tkfeather/icons/calendar.png
tkfeather/icons/camera-off.png
tkfeather/icons/camera.png
tkfeather/icons/cast.png
tkfeather/icons/check-circle.png
tkfeather/icons/check-square.png
tkfeather/icons/check.png
tkfeather/icons/chevron-down.png
tkfeather/icons/chevron-left.png
tkfeather/icons/chevron-right.png
tkfeather/icons/chevron-up.png
tkfeather/icons/chevrons-down.png
tkfeather/icons/chevrons-left.png
tkfeather/icons/chevrons-right.png
tkfeather/icons/chevrons-up.png
tkfeather/icons/chrome.png
tkfeather/icons/circle.png
tkfeather/icons/clipboard.png
tkfeather/icons/clock.png
tkfeather/icons/cloud-drizzle.png
tkfeather/icons/cloud-lightning.png
tkfeather/icons/cloud-off.png
tkfeather/icons/cloud-rain.png
tkfeather/icons/cloud-snow.png
tkfeather-1.0.1.dist-info/LICENSE
tkfeather-1.0.1.dist-info/METADATA
tkfeather-1.0.1.dist-info/WHEEL
tkfeather-1.0.1.dist-info/RECORD
