Metadata-Version: 2.1
Name: tkfeather
Version: 1.0.1
Summary: Feather icons for tkinter
Home-page: https://github.com/JRiggles/tkfeather
License: MIT
Keywords: tkinter,icons,Feather
Author: John Riggles
Author-email: jriggles@icloud.com
Requires-Python: >=3.12,<4.0
Classifier: License :: OSI Approved :: MIT License
Classifier: Programming Language :: Python :: 3
Classifier: Programming Language :: Python :: 3.12
Requires-Dist: pillow (>=9.2.0)
Project-URL: Repository, https://github.com/JRiggles/tkfeather
